hello_world/__init__.py
hello_world/hello_world_tool.py
hello_world/utils.py
kenakamu_pf_hello_world-0.0.1.dist-info/METADATA
kenakamu_pf_hello_world-0.0.1.dist-info/WHEEL
kenakamu_pf_hello_world-0.0.1.dist-info/entry_points.txt
kenakamu_pf_hello_world-0.0.1.dist-info/top_level.txt
kenakamu_pf_hello_world-0.0.1.dist-info/RECORD
